data/__init__.py
data/allowed_guesses.json
data/allowed_nordle.json
data/best_guess.json
data/best_guess_hard.json
data/best_guess_liar.json
data/best_guess_master.json
data/best_guess_nyt.json
data/curated_answers.json
data/freq_map.json
data/nyt_answers.json
data/responses.json
data/responses_master.json
wordle_autosolver-0.7.4.dist-info/LICENSE
wordle_autosolver-0.7.4.dist-info/METADATA
wordle_autosolver-0.7.4.dist-info/WHEEL
wordle_autosolver-0.7.4.dist-info/entry_points.txt
wordle_autosolver-0.7.4.dist-info/top_level.txt
wordle_autosolver-0.7.4.dist-info/RECORD
